ml_builder/Builder.py
ml_builder/__init__.py
ml_builder/app.py
ml_builder/cli.py
ml_builder/requirements.txt
ml_builder/.streamlit/config.toml
ml_builder/components/__init__.py
ml_builder/components/data_exploration/data_quality.py
ml_builder/components/data_exploration/feature_analysis.py
ml_builder/components/data_exploration/feature_relationships.py
ml_builder/components/data_exploration/render_advanced_automated_preprocessing.py
ml_builder/components/data_exploration/target_feature_analysis.py
ml_builder/components/data_exploration/utils/__init__.py
ml_builder/components/data_exploration/utils/data_quality_utils.py
ml_builder/components/data_exploration/utils/data_summary_utils.py
ml_builder/components/data_exploration/utils/feature_relationship_utils.py
ml_builder/components/data_exploration/utils/missing_values_utils.py
ml_builder/components/data_preprocessing/categorical_encoding.py
ml_builder/components/data_preprocessing/data_types_optimization.py
ml_builder/components/data_preprocessing/feature_binning.py
ml_builder/components/data_preprocessing/feature_creation.py
ml_builder/components/data_preprocessing/feature_management.py
ml_builder/components/data_preprocessing/final_data_review.py
ml_builder/components/data_preprocessing/missing_values_analysis.py
ml_builder/components/data_preprocessing/outlier_detection.py
ml_builder/components/data_preprocessing/train_test_split.py
ml_builder/components/data_preprocessing/zero_values_analysis.py
ml_builder/components/data_preprocessing/utils/__init__.py
ml_builder/components/data_preprocessing/utils/binning_utils.py
ml_builder/components/data_preprocessing/utils/categorical_encoding_utils.py
ml_builder/components/data_preprocessing/utils/outlier_detection_utils.py
ml_builder/components/data_preprocessing/utils/zero_values_utils.py
ml_builder/components/feature_selection/__init__.py
ml_builder/components/feature_selection/boruta_feature_selection.py
rai_mldev-1.2.0.dist-info/licenses/LICENSE
rai_mldev-1.2.0.dist-info/METADATA
rai_mldev-1.2.0.dist-info/WHEEL
rai_mldev-1.2.0.dist-info/entry_points.txt
rai_mldev-1.2.0.dist-info/top_level.txt
rai_mldev-1.2.0.dist-info/RECORD
