Metadata-Version: 2.4
Name: rai_mldev
Version: 1.2.0
Summary: A Streamlit-based ML model development guide promoting responsible AI
Author: Richard Wheeler
License: Proprietary
Project-URL: Homepage, https://github.com/R-I-Wheeler/RAI_MLdev
Project-URL: Issues, https://github.com/R-I-Wheeler/RAI_MLdev/issues
Keywords: machine-learning,streamlit,responsible-ai,model-development
Classifier: Development Status :: 4 - Beta
Classifier: Intended Audience :: Developers
Classifier: Intended Audience :: Science/Research
Classifier: License :: Other/Proprietary License
Classifier: License :: Free for non-commercial use
Classifier: Programming Language :: Python :: 3
Classifier: Programming Language :: Python :: 3.8
Classifier: Programming Language :: Python :: 3.9
Classifier: Programming Language :: Python :: 3.10
Classifier: Programming Language :: Python :: 3.11
Classifier: Programming Language :: Python :: 3.12
Classifier: Topic :: Scientific/Engineering :: Artificial Intelligence
Classifier: Topic :: Software Development :: Libraries :: Python Modules
Requires-Python: >=3.8
License-File: LICENSE
Requires-Dist: streamlit>=1.24.0
Requires-Dist: pandas>=1.5.0
Requires-Dist: numpy>=1.23.0
Requires-Dist: scikit-learn>=1.0.2
Requires-Dist: plotly<7.0.0,>=5.13.0
Requires-Dist: kaleido>=0.2.1
Requires-Dist: networkx>=3.1
Requires-Dist: category_encoders>=2.6.0
Requires-Dist: shap>=0.41.0
Requires-Dist: matplotlib>=3.6.0
Requires-Dist: seaborn>=0.12.0
Requires-Dist: scipy>=1.9.0
Requires-Dist: dython>=0.7.3
Requires-Dist: imbalanced-learn
Requires-Dist: optbinning>=0.20.0
Requires-Dist: streamlit-scroll-to-top
Requires-Dist: fairlearn>=0.7.0
Requires-Dist: Boruta>=0.3
Requires-Dist: xgboost>=2.1.4
Requires-Dist: lightgbm>=4.6.0
Requires-Dist: python-magic>=0.4.27; sys_platform != "win32"
Requires-Dist: python-magic-bin>=0.4.14; sys_platform == "win32"
Requires-Dist: optuna>=3.5.0
Requires-Dist: cmaes>=0.11.0
Requires-Dist: lime>=0.2.0
Requires-Dist: reportlab>=4.0.0
Requires-Dist: catboost>=1.2.0
Dynamic: license-file
